{
    "benchmark": "000300.XSHG", 
    "benchmark_last_value": 3307.1528320312, 
    "benchmark_pre_close": 3308.9721679688, 
    "date": "2016-08-26", 
    "minute": "15:00", 
    "portfolio_last_value": 24861.48986076342, 
    "portfolio_pre_close": 24673.48984931938, 
    "position": {
        "cash": 10890.49, 
        "securities": {
            "000402.XSHE": {
                "amount": 200.0, 
                "name": "\u91d1 \u878d \u8857", 
                "price": 11.909999847412
            }, 
            "000839.XSHE": {
                "amount": 200.0, 
                "name": "\u4e2d\u4fe1\u56fd\u5b89", 
                "price": 11.689999580383
            }, 
            "002424.XSHE": {
                "amount": 100.0, 
                "name": "\u8d35\u5dde\u767e\u7075", 
                "price": 23.979999542236
            }, 
            "600068.XSHG": {
                "amount": 300.0, 
                "name": "\u845b\u6d32\u575d", 
                "price": 8.1999998092651
            }, 
            "600663.XSHG": {
                "amount": 100.0, 
                "name": "\u9646\u5bb6\u5634", 
                "price": 25.090000152588
            }, 
            "601668.XSHG": {
                "amount": 300.0, 
                "name": "\u4e2d\u56fd\u5efa\u7b51", 
                "price": 6.2800002098083
            }
        }, 
        "value": 24861.48986076342
    }, 
    "pre_close": {
        "000402.XSHE": 12.079999923706, 
        "000839.XSHE": 11.170000076294, 
        "002424.XSHE": 23.479999542236, 
        "600068.XSHG": 7.9299998283386, 
        "600663.XSHG": 25.309999465942, 
        "601668.XSHG": 6.25
    }
}